kaz/__init__.py
kaz/constants.py
kaz/item.py
kaz/main.py
kaz/search.py
kaz/util.py
kaz-0.4.0.data/data/data/default_config
kaz-0.4.0.dist-info/LICENSE
kaz-0.4.0.dist-info/METADATA
kaz-0.4.0.dist-info/WHEEL
kaz-0.4.0.dist-info/entry_points.txt
kaz-0.4.0.dist-info/top_level.txt
kaz-0.4.0.dist-info/RECORD
