Metadata-Version: 2.1
Name: kaz
Version: 0.4.0
Summary: A simple storage cli
Home-page: https://github.com/clabe45/kaz
Author: Caleb Sacks
License: UNKNOWN
Project-URL: Bug Tracker, https://github.com/clabe45/kaz/issues
Keywords: storage store storing data cli tool minimalistic
Platform: UNKNOWN
Classifier: Development Status :: 4 - Beta
Classifier: Environment :: Console
Classifier: Intended Audience :: Developers
Classifier: License :: OSI Approved :: GNU General Public License v3 (GPLv3)
Classifier: Operating System :: MacOS :: MacOS X
Classifier: Operating System :: Microsoft :: Windows
Classifier: Operating System :: POSIX
Classifier: Programming Language :: Python
Classifier: Topic :: System
Classifier: Topic :: Utilities
Requires-Dist: click
Requires-Dist: colorama
